fritzing_stripboard/__init__.py
fritzing_stripboard/__main__.py
fritzing_stripboard/cli.py
fritzing_stripboard/constants.py
fritzing_stripboard/grid.py
fritzing_stripboard/types.py
fritzing_stripboard/zip.py
fritzing_stripboard/tests/__init__.py
fritzing_stripboard-1.0.0.dist-info/LICENSE
fritzing_stripboard-1.0.0.dist-info/METADATA
fritzing_stripboard-1.0.0.dist-info/WHEEL
fritzing_stripboard-1.0.0.dist-info/entry_points.txt
fritzing_stripboard-1.0.0.dist-info/top_level.txt
fritzing_stripboard-1.0.0.dist-info/RECORD
