Metadata-Version: 2.1
Name: fritzing-stripboard
Version: 1.0.0
Summary: Generate Fritzing components that match your stripboard
Home-page: https://github.com/coddingtonbear/fritzing-stripboard
Author: Adam Coddington
Author-email: me@adamcoddington.net
License: MIT
Project-URL: Changelog, https://fritzing-stripboard.readthedocs.io/en/latest/changelog.html
Project-URL: Issue Tracker, https://github.com/coddingtonbear/fritzing-stripboard/issues
Platform: UNKNOWN
Classifier: Development Status :: 5 - Production/Stable
Classifier: Intended Audience :: Developers
Classifier: License :: OSI Approved :: MIT License
Classifier: Operating System :: Unix
Classifier: Operating System :: POSIX
Classifier: Operating System :: Microsoft :: Windows
Classifier: Programming Language :: Python
Classifier: Programming Language :: Python :: 3
Classifier: Programming Language :: Python :: 3 :: Only
Classifier: Programming Language :: Python :: 3.6
Classifier: Programming Language :: Python :: 3.7
Classifier: Programming Language :: Python :: 3.8
Classifier: Programming Language :: Python :: 3.9
Classifier: Programming Language :: Python :: Implementation :: CPython
Classifier: Programming Language :: Python :: Implementation :: PyPy
Classifier: Topic :: Utilities
Requires-Python: >=3.6
License-File: LICENSE
Requires-Dist: pydantic (<2.0,>=1.10.7)
Requires-Dist: pyyaml (<7.0,>=6.0)
